fastq_wiper/__init__.py
fastq_wiper/wiper.py
tests/__init__.py
tests/test_wiper.py
fastqwiper-2024.1.93.dist-info/LICENSE
fastqwiper-2024.1.93.dist-info/METADATA
fastqwiper-2024.1.93.dist-info/WHEEL
fastqwiper-2024.1.93.dist-info/entry_points.txt
fastqwiper-2024.1.93.dist-info/top_level.txt
fastqwiper-2024.1.93.dist-info/RECORD
