Metadata-Version: 2.1
Name: fastqwiper
Version: 2024.1.93
Summary: An ensemble method to recover corrupted FASTQ files, drop or fix pesky lines, remove unpaired reads, and fix reads interleaving
Home-page: https://github.com/mazzalab/fastqwiper
Author: Tommaso Mazza
Author-email: bioinformatics@css-mendel.it
License: MIT
Project-URL: Source, https://github.com/mazzalab/fastqwiper
Project-URL: Tracker, https://github.com/mazzalab/fastqwiper/issues
Project-URL: Developmental plan, https://github.com/mazzalab/fastqwiper/projects
Keywords: genomics,ngs,fastq,bioinformatics
Classifier: Development Status :: 5 - Production/Stable
Classifier: Intended Audience :: Science/Research
Classifier: Programming Language :: Python :: 3.7
Classifier: Programming Language :: Python :: 3.8
Classifier: Programming Language :: Python :: 3.9
Classifier: Programming Language :: Python :: 3.10
Classifier: Programming Language :: Python :: 3.11
Classifier: Programming Language :: Python :: 3.12
Classifier: License :: OSI Approved :: MIT License
Classifier: Operating System :: OS Independent
Requires-Python: >=3.7,<3.13
License-File: LICENSE
Requires-Dist: setuptools
